sentience_sdk/__init__.py
sentience_sdk/api_client.py
sentience_sdk/api_response.py
sentience_sdk/configuration.py
sentience_sdk/exceptions.py
sentience_sdk/py.typed
sentience_sdk/rest.py
sentience_sdk/sentience_config.py
sentience_sdk/api/__init__.py
sentience_sdk/api/sentience_observation_api.py
sentience_sdk/models/__init__.py
sentience_sdk/models/sentience_applied_filters.py
sentience_sdk/models/sentience_bounding_box.py
sentience_sdk/models/sentience_credit_details.py
sentience_sdk/models/sentience_element_filter.py
sentience_sdk/models/sentience_element_states.py
sentience_sdk/models/sentience_error_response.py
sentience_sdk/models/sentience_insufficient_credits_error.py
sentience_sdk/models/sentience_interactable_element.py
sentience_sdk/models/sentience_layout_viewport.py
sentience_sdk/models/sentience_map_mode_response.py
sentience_sdk/models/sentience_observe200_response.py
sentience_sdk/models/sentience_observe_options.py
sentience_sdk/models/sentience_observe_request.py
sentience_sdk/models/sentience_output_format.py
sentience_sdk/models/sentience_plan_tier.py
sentience_sdk/models/sentience_processing_mode.py
sentience_sdk/models/sentience_proxy_failure.py
sentience_sdk/models/sentience_reader_mode_response.py
sentience_sdk/models/sentience_reader_mode_response_data.py
sentience_sdk/models/sentience_render_quality.py
sentience_sdk/models/sentience_response_metadata.py
sentience_sdk/models/sentience_subscription_details.py
sentience_sdk/models/sentience_subscription_inactive_error.py
sentience_sdk/models/sentience_viewport.py
sentience_sdk/models/sentience_visual_mode_response.py
sentience_sdk-0.2.2.dist-info/METADATA
sentience_sdk-0.2.2.dist-info/WHEEL
sentience_sdk-0.2.2.dist-info/top_level.txt
sentience_sdk-0.2.2.dist-info/RECORD
