Metadata-Version: 2.4
Name: sentience_sdk
Version: 0.2.2
Summary: Sentience API
Home-page: 
Author: Sentience API Support
Author-email: Sentience API Support <support@sentienceapi.com>
Project-URL: Repository, https://github.com/GIT_USER_ID/GIT_REPO_ID
Keywords: OpenAPI,OpenAPI-Generator,Sentience API
Requires-Python: >=3.9
Requires-Dist: urllib3<3.0.0,>=2.1.0
Requires-Dist: python-dateutil>=2.8.2
Requires-Dist: pydantic>=2
Requires-Dist: typing-extensions>=4.7.1
Dynamic: author
